README.md
setup.py
notimantionSdk.egg-info/PKG-INFO
notimantionSdk.egg-info/SOURCES.txt
notimantionSdk.egg-info/dependency_links.txt
notimantionSdk.egg-info/requires.txt
notimantionSdk.egg-info/top_level.txt
notimationSdk/__init__.py
notimationSdk/sdk.py