Metadata-Version: 2.1
Name: notimantionSdk
Version: 0.1.0
Summary: Sdk notimation
Home-page: https://github.com/gustavoghioldi/ghistylus
Author: Gustavo Ghioldi
Author-email: gustavoghioldi@gmail.com
License: UNKNOWN
Platform: UNKNOWN
Classifier: Programming Language :: Python :: 3
Classifier: License :: OSI Approved :: MIT License
Classifier: Operating System :: OS Independent
Requires-Python: >=3
